opendrop/__init__.py
opendrop/__main__.py
opendrop/cli.py
opendrop/client.py
opendrop/config.py
opendrop/server.py
opendrop/util.py
opendrop/certs/apple_root_ca.pem
opendrop-0.12.3.dist-info/LICENSE
opendrop-0.12.3.dist-info/METADATA
opendrop-0.12.3.dist-info/WHEEL
opendrop-0.12.3.dist-info/entry_points.txt
opendrop-0.12.3.dist-info/top_level.txt
opendrop-0.12.3.dist-info/RECORD
