Metadata-Version: 2.1
Name: opendrop
Version: 0.12.3
Summary: An open Apple AirDrop implementation
Home-page: https://owlink.org
Author: The Open Wireless Link Project
Author-email: mstute@seemoo.tu-darmstadt.de
License: UNKNOWN
Project-URL: Source, https://github.com/seemoo-lab/opendrop
Project-URL: Research Paper, https://usenix.org/conference/usenixsecurity19/presentation/stute
Keywords: cli
Platform: UNKNOWN
Classifier: License :: OSI Approved :: GNU General Public License v3 (GPLv3)
Classifier: Operating System :: MacOS
Classifier: Operating System :: POSIX :: Linux
Classifier: Natural Language :: English
Classifier: Programming Language :: Python :: 3
Classifier: Programming Language :: Python :: 3.6
Classifier: Programming Language :: Python :: 3.7
Classifier: Programming Language :: Python :: 3.8
Classifier: Programming Language :: Python :: 3.9
Requires-Python: >=3.6
Requires-Dist: Pillow
Requires-Dist: fleep
Requires-Dist: ifaddr
Requires-Dist: libarchive-c
Requires-Dist: requests
Requires-Dist: requests-toolbelt
Requires-Dist: zeroconf (>=0.24.2)
